__init__.py
bar.py
utils/__init__.py
utils/foo.py
myuvstudy_py-0.1.9.dist-info/METADATA
myuvstudy_py-0.1.9.dist-info/WHEEL
myuvstudy_py-0.1.9.dist-info/top_level.txt
myuvstudy_py-0.1.9.dist-info/RECORD
