Metadata-Version: 2.4
Name: MyUVStudy.py
Version: 0.1.9
Summary: 这是一个UV学习的python项目
Requires-Python: >=3.13
Requires-Dist: basiclibrary-py>=0.6.55
